dbaas_aclapi/__init__.py
dbaas_aclapi/acl_base_client.py
dbaas_aclapi/exceptions.py
dbaas_aclapi/helpers.py
dbaas_aclapi/models.py
dbaas_aclapi/tasks.py
dbaas_aclapi/util.py
dbaas_aclapi/migrations/0001_initial.py
dbaas_aclapi/migrations/0002_auto__add_unique_instancebind_instance_bind_address__add_unique_databa.py
dbaas_aclapi/migrations/0003_auto__del_instancebind__del_unique_instancebind_instance_bind_address_.py
dbaas_aclapi/migrations/0004_auto__del_unique_databaseinfrainstancebind_instance_bind_address__add_.py
dbaas_aclapi/migrations/0005_auto__add_field_databaseinfrainstancebind_instance_port__add_field_dat.py
dbaas_aclapi/migrations/0006_auto__del_unique_databaseinfrainstancebind_instance_bind_address_datab.py
dbaas_aclapi/migrations/0007_auto__chg_field_databasebind_database.py
dbaas_aclapi/migrations/0008_auto__add_aclapijob__add_unique_aclapijob_job_id_job_operation.py
dbaas_aclapi/migrations/0009_auto__del_unique_databaseinfrainstancebind_instance_instance_port_bind.py
dbaas_aclapi/migrations/0010_auto__add_unique_databaseinfrainstancebind_instance_instance_port_bind.py
dbaas_aclapi/migrations/0011_auto__del_databaseinfrainstancebind__del_unique_databaseinfrainstanceb.py
dbaas_aclapi/migrations/__init__.py
dbaas_aclapi-1.0.14.dist-info/AUTHORS.rst
dbaas_aclapi-1.0.14.dist-info/LICENSE
dbaas_aclapi-1.0.14.dist-info/METADATA
dbaas_aclapi-1.0.14.dist-info/WHEEL
dbaas_aclapi-1.0.14.dist-info/top_level.txt
dbaas_aclapi-1.0.14.dist-info/RECORD
