Metadata-Version: 2.1
Name: dbaas-aclapi
Version: 1.0.14
Summary: ACL API integration for DBaaS
Home-page: https://github.com/felippemr/dbaas-aclapi
Author: Felippe da Motta Raposo
Author-email: felippe.gestec@corp.globo.com
License: BSD
Keywords: dbaas_aclapi
Platform: UNKNOWN
Classifier: Development Status :: 2 - Pre-Alpha
Classifier: Intended Audience :: Developers
Classifier: License :: OSI Approved :: BSD License
Classifier: Natural Language :: English
Classifier: Programming Language :: Python :: 2
Classifier: Programming Language :: Python :: 2.6
Classifier: Programming Language :: Python :: 2.7
Classifier: Programming Language :: Python :: 3
Classifier: Programming Language :: Python :: 3.3
Classifier: Programming Language :: Python :: 3.4
Requires-Dist: django (==1.6.10)
Requires-Dist: urllib3 (==1.7.1)
Requires-Dist: dbaas-credentials (==1.1.9)
Requires-Dist: GloboNetworkAPI (==0.6.24)
